app/__init__.py
app/ytest.py
ytest/__init__.py
ytest/app.py
ytest-0.1.4.dist-info/DESCRIPTION.rst
ytest-0.1.4.dist-info/METADATA
ytest-0.1.4.dist-info/RECORD
ytest-0.1.4.dist-info/WHEEL
ytest-0.1.4.dist-info/entry_points.txt
ytest-0.1.4.dist-info/metadata.json
ytest-0.1.4.dist-info/top_level.txt
ytest-0.1.4.dist-info/zip-safe
