Metadata-Version: 2.0
Name: ytest
Version: 0.1.4
Summary: a demo project
Home-page: https://github.com/yotong/ytest
Author: yotong
Author-email: yotong@qq.com
License: MIT
Keywords: python ytest demo
Platform: UNKNOWN
Requires-Dist: requests
